streamlit_markmap/__init__.py
streamlit_markmap-1.0.1.dist-info/LICENSE
streamlit_markmap-1.0.1.dist-info/METADATA
streamlit_markmap-1.0.1.dist-info/WHEEL
streamlit_markmap-1.0.1.dist-info/top_level.txt
streamlit_markmap-1.0.1.dist-info/RECORD
