Metadata-Version: 2.1
Name: streamlit-markmap
Version: 1.0.1
Summary: markmap
Home-page: 
Author: echoopen
Author-email: 632019805@qq.com
Requires-Python: >=3.6
License-File: LICENSE
Requires-Dist: streamlit (>=0.63)
